MANIFEST.in
README.rst
setup.py
pocker/VERSION
pocker/__init__.py
pocker/exceptions.py
pocker/parsers.py
pocker/pocker.py
pocker/utils.py
pocker/version.py
pocker.egg-info/.PKG-INFO.un~
pocker.egg-info/PKG-INFO
pocker.egg-info/SOURCES.txt
pocker.egg-info/dependency_links.txt
pocker.egg-info/top_level.txt