Metadata-Version: 1.1
Name: pocker
Version: 0.1.5
Summary: Python wrapper for docker console client
Home-page: https://bitbucket.org/levelupdev/pocker
Author: Sergey Anuchin
Author-email: sergunich@gmail.com
License: MIT
Keywords: docker client
Platform: UNKNOWN
Classifier: Development Status :: 4 - Beta
Classifier: Intended Audience :: Developers
Classifier: Intended Audience :: Information Technology
Classifier: License :: OSI Approved :: MIT License
Classifier: Natural Language :: English
Classifier: Operating System :: POSIX :: Linux
Classifier: Programming Language :: Python :: 2.6
Classifier: Programming Language :: Python :: 2.7
Classifier: Programming Language :: Python :: 2 :: Only 
Classifier: Topic :: System :: Systems Administration
Classifier: Topic :: Utilities
